slightwind/__init__.py
slightwind/funs_.py
slightwind/slightwind.py
slightwind/Math/__init__.py
slightwind-0.0.3.dist-info/LICENSE
slightwind-0.0.3.dist-info/METADATA
slightwind-0.0.3.dist-info/WHEEL
slightwind-0.0.3.dist-info/top_level.txt
slightwind-0.0.3.dist-info/RECORD
