Metadata-Version: 2.1
Name: slightwind
Version: 0.0.3
Summary: Some commonly used functions.
Home-page: UNKNOWN
Author: Slightwind
Author-email: am473ur@gmail.com
License: UNKNOWN
Platform: UNKNOWN
Classifier: Programming Language :: Python :: 3
License-File: LICENSE
